pydtmc/__init__.py
pydtmc/assessments.py
pydtmc/base_classes.py
pydtmc/computations.py
pydtmc/custom_types.py
pydtmc/decorators.py
pydtmc/exceptions.py
pydtmc/files_io.py
pydtmc/fitting.py
pydtmc/generators.py
pydtmc/hidden_markov_model.py
pydtmc/markov_chain.py
pydtmc/measures.py
pydtmc/plotting.py
pydtmc/simulations.py
pydtmc/utilities.py
pydtmc/validation.py
PyDTMC-8.7.0.dist-info/LICENSE.md
PyDTMC-8.7.0.dist-info/METADATA
PyDTMC-8.7.0.dist-info/WHEEL
PyDTMC-8.7.0.dist-info/top_level.txt
PyDTMC-8.7.0.dist-info/RECORD
