Metadata-Version: 2.1
Name: PyDTMC
Version: 8.7.0
Summary: A full-featured and lightweight library for discrete-time Markov chains analysis.
Home-page: https://github.com/TommasoBelluzzo/PyDTMC
Author: Tommaso Belluzzo
Author-email: tommaso.belluzzo@gmail.com
Maintainer: Tommaso Belluzzo
Maintainer-email: tommaso.belluzzo@gmail.com
License: MIT
Project-URL: Bug Tracker, https://github.com/TommasoBelluzzo/PyDTMC/issues
Project-URL: Donation, https://www.paypal.com/donate?hosted_button_id=D8LH6DNYN7EN8
Keywords: markov-chain,markov-chains,markov-model,markov-models,markov-state-model,markov-state-models,hidden-markov-model,hidden-markov-models,mathematics,statistics,probability,stochastic-process,stochastic-processes,analysis,fitting,simulation
Platform: any
Classifier: Development Status :: 5 - Production/Stable
Classifier: License :: OSI Approved :: MIT License
Classifier: Natural Language :: English
Classifier: Operating System :: OS Independent
Classifier: Programming Language :: Python :: 3
Classifier: Programming Language :: Python :: 3 :: Only
Classifier: Programming Language :: Python :: 3.8
Classifier: Programming Language :: Python :: 3.9
Classifier: Programming Language :: Python :: 3.10
Classifier: Programming Language :: Python :: 3.11
Classifier: Programming Language :: Python :: 3.12
Classifier: Intended Audience :: Education
Classifier: Intended Audience :: Financial and Insurance Industry
Classifier: Intended Audience :: Science/Research
Classifier: Intended Audience :: Other Audience
Classifier: Topic :: Education
Classifier: Topic :: Office/Business
Classifier: Topic :: Scientific/Engineering
Classifier: Topic :: Text Processing
Classifier: Topic :: Other/Nonlisted Topic
Requires-Python: >=3.8
License-File: LICENSE.md
Requires-Dist: matplotlib <=3.7.3
Requires-Dist: networkx
Requires-Dist: numpy
Requires-Dist: scipy
Provides-Extra: build
Requires-Dist: setuptools ; extra == 'build'
Requires-Dist: wheel ; extra == 'build'
Requires-Dist: twine ; extra == 'build'
Provides-Extra: docs
Requires-Dist: docutils ; extra == 'docs'
Requires-Dist: typing-extensions ; extra == 'docs'
Requires-Dist: sphinx <=7.1.2 ; extra == 'docs'
Requires-Dist: sphinx-autodoc-typehints ; extra == 'docs'
Requires-Dist: sphinx-rtd-theme ; extra == 'docs'
Provides-Extra: lint
Requires-Dist: flake8 ; extra == 'lint'
Requires-Dist: pylint ; extra == 'lint'
Provides-Extra: package
Requires-Dist: defusedxml ; extra == 'package'
Requires-Dist: numpydoc ; extra == 'package'
Requires-Dist: pandas ; extra == 'package'
Requires-Dist: pydot ; extra == 'package'
Provides-Extra: tests
Requires-Dist: coverage ; extra == 'tests'
Requires-Dist: pytest ; extra == 'tests'
Requires-Dist: pytest-benchmark ; extra == 'tests'
Requires-Dist: pytest-cov ; extra == 'tests'
Requires-Dist: coveralls ; extra == 'tests'
